mysqlonsocket/__init__.py
mysqlonsocket/client.py
mysqlonsocket/config.py
mysqlonsocket/configrations.py
mysqlonsocket/server.py
mysqlonsocket/test_client.py
mysqlonsocket/test_server.py
mysqlonsocket/utils.py
mysqlonsocket-0.0.1.dist-info/LICENSE.txt
mysqlonsocket-0.0.1.dist-info/METADATA
mysqlonsocket-0.0.1.dist-info/WHEEL
mysqlonsocket-0.0.1.dist-info/top_level.txt
mysqlonsocket-0.0.1.dist-info/RECORD
